bocha_search_mcp/__init__.py
bocha_search_mcp/server.py
mseep_bocha_search_mcp-0.0.3.dist-info/METADATA
mseep_bocha_search_mcp-0.0.3.dist-info/WHEEL
mseep_bocha_search_mcp-0.0.3.dist-info/entry_points.txt
mseep_bocha_search_mcp-0.0.3.dist-info/top_level.txt
mseep_bocha_search_mcp-0.0.3.dist-info/RECORD
