Metadata-Version: 2.4
Name: mseep-bocha-search-mcp
Version: 0.0.3
Summary: A
Author-email: mseep <support@skydeck.ai>
Requires-Python: >=3.12
Requires-Dist: mcp[cli]>=1.6.0
